[
  {
    "symbol": "ETHBTC",
    "priceChange": "-0.00078300",
    "priceChangePercent": "-1.387",
    "weightedAvgPrice": "0.05603742",
    "prevClosePrice": "0.05645400",
    "lastPrice": "0.05567000",
    "lastQty": "0.19900000",
    "bidPrice": "0.05567000",
    "bidQty": "3.55100000",
    "askPrice": "0.05572000",
    "askQty": "4.22900000",
    "openPrice": "0.05645300",
    "highPrice": "0.05682600",
    "lowPrice": "0.05541000",
    "volume": "127839.29500000",
    "quoteVolume": "7163.78470907",
    "openTime": 1533816600113,
    "closeTime": 1533903000113,
    "firstId": 76658697,
    "lastId": 76811200,
    "count": 152504
  },
  {
    "symbol": "LTCBTC",
    "priceChange": "-0.00008400",
    "priceChangePercent": "-0.867",
    "weightedAvgPrice": "0.00970283",
    "prevClosePrice": "0.00968300",
    "lastPrice": "0.00959900",
    "lastQty": "0.62000000",
    "bidPrice": "0.00958100",
    "bidQty": "2.14000000",
    "askPrice": "0.00959600",
    "askQty": "19.71000000",
    "openPrice": "0.00968300",
    "highPrice": "0.00985100",
    "lowPrice": "0.00955600",
    "volume": "158630.26000000",
    "quoteVolume": "1539.16216431",
    "openTime": 1533816600010,
    "closeTime": 1533903000010,
    "firstId": 14950009,
    "lastId": 14981893,
    "count": 31885
  }
]